MANIFEST.in
README.md
README.rst
pipeto.py
setup.py
pipeto.egg-info/PKG-INFO
pipeto.egg-info/SOURCES.txt
pipeto.egg-info/dependency_links.txt
pipeto.egg-info/top_level.txt