Metadata-Version: 1.1
Name: pipeto
Version: 0.1.1
Summary: linux pipe style for python
Home-page: https://github.com/v2e4lisp/pipeto
Author: Yan Wenjun
Author-email: mylastnameisyan@gmail.com
License: MIT
Platform: UNKNOWN
Classifier: License :: OSI Approved :: MIT License
Classifier: Topic :: Software Development :: Libraries
